adaptfilt/__init__.py
adaptfilt/_paramcheck.py
adaptfilt/ap.py
adaptfilt/lms.py
adaptfilt/misc.py
adaptfilt/nlms.py
adaptfilt/nlmsru.py
adaptfilt/rls.py
adaptfilt-0.3.dist-info/LICENSE.txt
adaptfilt-0.3.dist-info/METADATA
adaptfilt-0.3.dist-info/WHEEL
adaptfilt-0.3.dist-info/top_level.txt
adaptfilt-0.3.dist-info/RECORD
