Metadata-Version: 2.1
Name: adaptfilt
Version: 0.3
Summary: Adaptive filtering module for Python
Home-page: https://github.com/Wramberg/adaptfilt
Author: Jesper Wramberg & Mathias Tausen
Author-email: jesper.wramberg@gmail.com & mathias.tausen@gmail.com
License: MIT
Keywords: adaptive filter,adaptive filtering,signal processing,lms,apa,nlms,rls
Classifier: Development Status :: 5 - Production/Stable
Classifier: Programming Language :: Python
Classifier: Intended Audience :: Education
Classifier: Intended Audience :: Developers
Classifier: Topic :: Software Development :: Libraries :: Python Modules
License-File: LICENSE.txt
